setup.py
channel/__init__.py
channel/camunda_cloud_channel.py
channel/channel_options.py
channel/insecure_channel.py
channel/secure_channel.py
channel/utils.py
client/__init__.py
client/client.py
client/sync_client.py
errors/__init__.py
errors/credentials_errors.py
errors/job_errors.py
errors/message_errors.py
errors/process_errors.py
errors/pyzeebe_errors.py
errors/zeebe_errors.py
function_tools/__init__.py
function_tools/async_tools.py
function_tools/dict_tools.py
function_tools/parameter_tools.py
grpc_internals/__init__.py
grpc_internals/zeebe_adapter.py
grpc_internals/zeebe_adapter_base.py
grpc_internals/zeebe_job_adapter.py
grpc_internals/zeebe_message_adapter.py
grpc_internals/zeebe_process_adapter.py
job/__init__.py
job/job.py
job/job_status.py
mpyzeebe/__init__.py
mpyzeebe.egg-info/PKG-INFO
mpyzeebe.egg-info/SOURCES.txt
mpyzeebe.egg-info/dependency_links.txt
mpyzeebe.egg-info/requires.txt
mpyzeebe.egg-info/top_level.txt
mpyzeebe/client/__init__.py
mpyzeebe/client/client.py
mpyzeebe/credentials/__init__.py
mpyzeebe/credentials/base_credentials.py
mpyzeebe/credentials/camunda_cloud_credentials.py
mpyzeebe/credentials/oauth_credentials.py
mpyzeebe/decorators/__init__.py
mpyzeebe/decorators/zeebe_decorator_base.py
mpyzeebe/exceptions/__init__.py
mpyzeebe/exceptions/credentials_exceptions.py
mpyzeebe/exceptions/job_exceptions.py
mpyzeebe/exceptions/message_exceptions.py
mpyzeebe/exceptions/pyzeebe_exceptions.py
mpyzeebe/exceptions/workflow_exceptions.py
mpyzeebe/exceptions/zeebe_exceptions.py
mpyzeebe/grpc_internals/__init__.py
mpyzeebe/grpc_internals/zeebe_adapter.py
mpyzeebe/grpc_internals/zeebe_adapter_base.py
mpyzeebe/grpc_internals/zeebe_job_adapter.py
mpyzeebe/grpc_internals/zeebe_message_adapter.py
mpyzeebe/grpc_internals/zeebe_workflow_adapter.py
mpyzeebe/job/__init__.py
mpyzeebe/job/job.py
mpyzeebe/job/job_status.py
mpyzeebe/task/__init__.py
mpyzeebe/task/exception_handler.py
mpyzeebe/task/task.py
mpyzeebe/task/task_decorator.py
mpyzeebe/worker/__init__.py
mpyzeebe/worker/task_handler.py
mpyzeebe/worker/task_router.py
mpyzeebe/worker/worker.py
task/__init__.py
task/exception_handler.py
task/task.py
